LICENSE.md
README.md
setup.cfg
setup.py
junix/__init__.py
junix/cli.py
junix/junix.py
junix.egg-info/PKG-INFO
junix.egg-info/SOURCES.txt
junix.egg-info/dependency_links.txt
junix.egg-info/entry_points.txt
junix.egg-info/requires.txt
junix.egg-info/top_level.txt