Metadata-Version: 1.0
Name: junix
Version: 0.1.5
Summary: Utils to export images from Jupyter notebook
Home-page: UNKNOWN
Author: Damien Marlier
Author-email: damien.marlier@hotmail.fr
License: UNKNOWN
Platform: UNKNOWN
